{"__symbolic":"module","version":4,"metadata":{"AioAuthV01Service":{"__symbolic":"class","decorators":[{"__symbolic":"call","expression":{"__symbolic":"reference","module":"@angular/core","name":"Injectable","line":4,"character":1},"arguments":[{"providedIn":"root"}]}],"members":{"__ctor__":[{"__symbolic":"constructor","parameterDecorators":[[{"__symbolic":"call","expression":{"__symbolic":"reference","module":"@angular/core","name":"Inject","line":13,"character":15},"arguments":[{"__symbolic":"reference","name":"AuthConfigService"}]}],null],"parameters":[{"__symbolic":"reference","name":"AuthConfig"},{"__symbolic":"reference","name":"ɵa"}]}],"getLoginRedirect":[{"__symbolic":"method"}]},"statics":{"fbProvider":"","GmProvider":"default","ngInjectableDef":{}}},"AioAuthV01Component":{"__symbolic":"class","decorators":[{"__symbolic":"call","expression":{"__symbolic":"reference","module":"@angular/core","name":"Component","line":3,"character":1},"arguments":[{"selector":"lib-aio-auth-v01","template":"\n    <p>\n      aio-auth-v01 works!\n    </p>\n  ","styles":[]}]}],"members":{"__ctor__":[{"__symbolic":"constructor"}],"ngOnInit":[{"__symbolic":"method"}]}},"AioAuthV01Module":{"__symbolic":"class","decorators":[{"__symbolic":"call","expression":{"__symbolic":"reference","module":"@angular/core","name":"NgModule","line":17,"character":1},"arguments":[{"declarations":[{"__symbolic":"reference","name":"AioAuthV01Component"},{"__symbolic":"reference","name":"ɵb"},{"__symbolic":"reference","name":"ɵc"},{"__symbolic":"reference","name":"ɵd"},{"__symbolic":"reference","name":"ɵe"},{"__symbolic":"reference","name":"ɵf"},{"__symbolic":"reference","name":"ɵg"}],"imports":[{"__symbolic":"reference","module":"@angular/common","name":"CommonModule","line":20,"character":4},{"__symbolic":"reference","module":"@angular/forms","name":"FormsModule","line":21,"character":4},{"__symbolic":"reference","module":"@angular/forms","name":"ReactiveFormsModule","line":22,"character":4},{"__symbolic":"reference","module":"@angular/common/http","name":"HttpClientModule","line":23,"character":4},{"__symbolic":"reference","module":"@angular/router","name":"RouterModule","line":24,"character":4}],"providers":[{"provide":{"__symbolic":"reference","module":"@angular/common/http","name":"HTTP_INTERCEPTORS","line":27,"character":15},"useClass":{"__symbolic":"reference","name":"ɵh"},"multi":true},{"provide":{"__symbolic":"reference","module":"@angular/common/http","name":"HTTP_INTERCEPTORS","line":28,"character":15},"useClass":{"__symbolic":"reference","name":"ɵi"},"multi":true}],"exports":[{"__symbolic":"reference","name":"AioAuthV01Component"},{"__symbolic":"reference","name":"ɵb"},{"__symbolic":"reference","name":"ɵc"},{"__symbolic":"reference","name":"ɵd"},{"__symbolic":"reference","name":"ɵe"},{"__symbolic":"reference","name":"ɵf"},{"__symbolic":"reference","name":"ɵg"}]}]}],"members":{},"statics":{"forRoot":{"__symbolic":"function","parameters":["config"],"value":{"ngModule":{"__symbolic":"reference","name":"AioAuthV01Module"},"providers":[{"__symbolic":"reference","name":"AioAuthV01Service"},{"provide":{"__symbolic":"reference","name":"AuthConfigService"},"useValue":{"__symbolic":"reference","name":"config"}}]}}}},"AuthConfig":{"__symbolic":"interface"},"AuthConfigService":{"__symbolic":"new","expression":{"__symbolic":"reference","module":"@angular/core","name":"InjectionToken","line":17,"character":37},"arguments":["AuthConfig"]},"AuthGuard":{"__symbolic":"class","decorators":[{"__symbolic":"call","expression":{"__symbolic":"reference","module":"@angular/core","name":"Injectable","line":3,"character":1},"arguments":[{"providedIn":"root"}]}],"members":{"__ctor__":[{"__symbolic":"constructor","parameters":[{"__symbolic":"reference","module":"@angular/router","name":"Router","line":6,"character":32}]}],"canActivate":[{"__symbolic":"method"}]},"statics":{"ngInjectableDef":{}}},"ɵa":{"__symbolic":"class","decorators":[{"__symbolic":"call","expression":{"__symbolic":"reference","module":"@angular/core","name":"Injectable","line":9,"character":1},"arguments":[{"providedIn":"root"}]}],"members":{"__ctor__":[{"__symbolic":"constructor","parameterDecorators":[null,[{"__symbolic":"call","expression":{"__symbolic":"reference","module":"@angular/core","name":"Inject","line":14,"character":44},"arguments":[{"__symbolic":"reference","name":"AuthConfigService"}]}]],"parameters":[{"__symbolic":"reference","module":"@angular/common/http","name":"HttpClient","line":14,"character":30},{"__symbolic":"reference","name":"AuthConfig"}]}],"login":[{"__symbolic":"method"}],"FBlogin":[{"__symbolic":"method"}],"logout":[{"__symbolic":"method"}],"register":[{"__symbolic":"method"}],"checkEmailExis":[{"__symbolic":"method"}],"fbRegister":[{"__symbolic":"method"}],"getInstaUserData":[{"__symbolic":"method"}]},"statics":{"ngInjectableDef":{}}},"ɵb":{"__symbolic":"class","decorators":[{"__symbolic":"call","expression":{"__symbolic":"reference","module":"@angular/core","name":"Component","line":7,"character":1},"arguments":[{"selector":"td-login","template":"<div id=\"logreg-forms\" *ngIf=\"showLogin\">\n    <form class=\"form-signin\" [formGroup]=\"loginForm\" (ngSubmit)=\"onSubmit()\">\n        <h1 class=\"h3 mb-3 font-weight-normal\" style=\"text-align: center\"> Sign in</h1>         \n\n        <div *ngIf=\"error\" class=\"text-danger\">{{error}}</div>\n        <div class=\"form-group\">\n            <label for=\"username\">Username</label>\n            <input type=\"text\" formControlName=\"username\" class=\"form-control\" [ngClass]=\"{ 'is-invalid': submitted && f.username.errors }\" />\n            <div *ngIf=\"submitted && f.username.errors\" class=\"invalid-feedback\">\n                <div *ngIf=\"f.username.errors.required\">Username is required</div>\n            </div>\n        </div>\n        <div class=\"form-group\">\n            <label for=\"password\">Password</label>\n            <input type=\"password\" formControlName=\"password\" class=\"form-control\" [ngClass]=\"{ 'is-invalid': submitted && f.password.errors }\" />\n            <div *ngIf=\"submitted && f.password.errors\" class=\"invalid-feedback\">\n                <div *ngIf=\"f.password.errors.required\">Password is required</div>\n            </div>\n        </div>\n        <div class=\"form-group\">\n            <button [disabled]=\"loading\" class=\"btn btn-success btn-block\">Login</button>       \n        </div> \n         \n        <a href=\"#\" id=\"forgot_pswd\">Forgot password?</a>\n        <a routerLink=\"/register\" id=\"newAccount\" class=\"pull-right\">Sign Up New Account</a>\n        <hr>\n        \n        </form>\n \n       \n</div>\n\n\n<div class=\"well\"  *ngIf=\"!showLogin\">\n        You are loggedIN with following details:<br/>\n\n        Username : {{currentUser.username}}\n        <p> First Name : {{currentUser.firstName}} </p>\n        <p> <td-log-out></td-log-out></p>\n    </div>","styles":[""]}]}],"members":{"__ctor__":[{"__symbolic":"constructor","parameterDecorators":[null,null,null,null,[{"__symbolic":"call","expression":{"__symbolic":"reference","module":"@angular/core","name":"Inject","line":27,"character":9},"arguments":[{"__symbolic":"reference","name":"AuthConfigService"}]}]],"parameters":[{"__symbolic":"reference","module":"@angular/forms","name":"FormBuilder","line":23,"character":29},{"__symbolic":"reference","module":"@angular/router","name":"ActivatedRoute","line":24,"character":23},{"__symbolic":"reference","module":"@angular/router","name":"Router","line":25,"character":24},{"__symbolic":"reference","name":"ɵa"},{"__symbolic":"reference","name":"AuthConfig"}]}],"ngOnInit":[{"__symbolic":"method"}],"onSubmit":[{"__symbolic":"method"}]}},"ɵc":{"__symbolic":"class","decorators":[{"__symbolic":"call","expression":{"__symbolic":"reference","module":"@angular/core","name":"Component","line":9,"character":1},"arguments":[{"selector":"td-register","template":"<!-- main app container -->\n\n              <h3 class=\"text-justify\">{{ heading }}</h3>\n              <div *ngIf=\"error\" class=\"alert alert-danger\">{{error}}</div>\n              <div *ngIf=\"customMsg\" class=\"alert alert-{{custClass}}\">{{customMsg}}</div>\n\n              <form *ngIf=\"frmShow\" [formGroup]=\"registerForm\" (ngSubmit)=\"onSubmit()\">                \n\n                  <div class=\"form-group\">\n                      <label>First Name</label>\n                      <input type=\"text\" tabindex=\"-1\" formControlName=\"firstName\" class=\"form-control\" [ngClass]=\"{ 'is-invalid': submitted && f.firstName.errors }\" />\n                      <div *ngIf=\"submitted && f.firstName.errors\" class=\"invalid-feedback\">\n                          <div *ngIf=\"f.firstName.errors.required\">First Name is required</div>\n                      </div>\n                  </div>\n                  <div class=\"form-group\">\n                      <label>Last Name</label>\n                      <input type=\"text\" formControlName=\"lastName\" class=\"form-control\" [ngClass]=\"{ 'is-invalid': submitted && f.lastName.errors }\" />\n                      <div *ngIf=\"submitted && f.lastName.errors\" class=\"invalid-feedback\">\n                          <div *ngIf=\"f.lastName.errors.required\">Last Name is required</div>\n                      </div>\n                  </div>\n                  <div class=\"form-group\">\n                      <label>Email</label>\n                      <input type=\"text\" (blur)=\"isEmailUnique(emailAdd.value)\"  id=\"email\" formControlName=\"email\" #emailAdd  class=\"form-control\" [ngClass]=\"{ 'is-invalid': submitted && f.email.errors }\" />\n                    \n                      <div *ngIf=\"submitted && f.email.errors\" class=\"invalid-feedback\">\n                          <div *ngIf=\"f.email.errors.required\">Email is required</div>\n                          <div *ngIf=\"f.email.errors.email\">Email must be a valid email address</div>\n                      </div>\n                        <div *ngIf=\"userExist\" class=\"invalid-feedback\">This Email is already exists.</div>\n                  </div>\n                  <div class=\"form-group\">\n                      <label>Password</label>\n                      <input type=\"password\" formControlName=\"password\" class=\"form-control\" [ngClass]=\"{ 'is-invalid': submitted && f.password.errors }\" />\n                      <div *ngIf=\"submitted && f.password.errors\" class=\"invalid-feedback\">\n                          <div *ngIf=\"f.password.errors.required\">Password is required</div>\n                          <div *ngIf=\"f.password.errors.minlength\">Password must be at least 6 characters</div>\n                      </div>\n                  </div>\n                  <div class=\"form-group\">\n                      <label>Confirm Password</label>\n                      <input type=\"password\" formControlName=\"confirmPassword\" class=\"form-control\" [ngClass]=\"{ 'is-invalid': submitted && f.confirmPassword.errors }\" />\n                      <div *ngIf=\"submitted && f.confirmPassword.errors\" class=\"invalid-feedback\">\n                          <div *ngIf=\"f.confirmPassword.errors.required\">Confirm Password is required</div>\n                          <div *ngIf=\"f.confirmPassword.errors.mustMatch\">Passwords must match</div>\n                      </div>\n                  </div>\n                  <div class=\"form-group\">\n                      <button class=\"btn btn-primary\">{{RegBtnText}}</button>\n                      <a routerLink=\"/login\" routerLinkActive=\"active\" class=\"pull-right\">{{loginBtnText}}</a>\n                  </div>\n              </form>","styles":[".regForm{padding:10px}"]}]}],"members":{"loginBtnText":[{"__symbolic":"property","decorators":[{"__symbolic":"call","expression":{"__symbolic":"reference","module":"@angular/core","name":"Input","line":24,"character":3}}]}],"RegBtnText":[{"__symbolic":"property","decorators":[{"__symbolic":"call","expression":{"__symbolic":"reference","module":"@angular/core","name":"Input","line":25,"character":3}}]}],"heading":[{"__symbolic":"property","decorators":[{"__symbolic":"call","expression":{"__symbolic":"reference","module":"@angular/core","name":"Input","line":26,"character":3}}]}],"__ctor__":[{"__symbolic":"constructor","parameterDecorators":[null,null,null,null,[{"__symbolic":"call","expression":{"__symbolic":"reference","module":"@angular/core","name":"Inject","line":34,"character":5},"arguments":[{"__symbolic":"reference","name":"AuthConfigService"}]}]],"parameters":[{"__symbolic":"reference","module":"@angular/forms","name":"FormBuilder","line":31,"character":27},{"__symbolic":"reference","module":"@angular/router","name":"ActivatedRoute","line":31,"character":56},{"__symbolic":"reference","module":"@angular/router","name":"Router","line":32,"character":20},{"__symbolic":"reference","name":"ɵa"},{"__symbolic":"reference","name":"AuthConfig"}]}],"onSubmit":[{"__symbolic":"method"}],"ngOnInit":[{"__symbolic":"method"}],"isEmailUnique":[{"__symbolic":"method"}]}},"ɵd":{"__symbolic":"class","decorators":[{"__symbolic":"call","expression":{"__symbolic":"reference","module":"@angular/core","name":"Component","line":9,"character":1},"arguments":[{"selector":"lib-fblogin","template":"<button class=\"btn facebook-btn social-btn btn-facebook\"  (click)=\"fbLogin()\" type=\"button\"> <span> {{ btnText }}</span> <i class=\"fa fa-facebook\"></i> </button>","styles":[""]}]}],"members":{"btnText":[{"__symbolic":"property","decorators":[{"__symbolic":"call","expression":{"__symbolic":"reference","module":"@angular/core","name":"Input","line":23,"character":3}}]}],"__ctor__":[{"__symbolic":"constructor","parameterDecorators":[[{"__symbolic":"call","expression":{"__symbolic":"reference","module":"@angular/core","name":"Inject","line":24,"character":15},"arguments":[{"__symbolic":"reference","name":"AuthConfigService"}]}],null,null,null],"parameters":[{"__symbolic":"reference","name":"AuthConfig"},{"__symbolic":"reference","module":"@angular/router","name":"Router","line":24,"character":89},{"__symbolic":"reference","module":"@angular/router","name":"ActivatedRoute","line":24,"character":112},{"__symbolic":"reference","name":"ɵa"}]}],"ngAfterViewInit":[{"__symbolic":"method"}],"ngOnInit":[{"__symbolic":"method"}],"fbLogin":[{"__symbolic":"method"}],"getFbUserData":[{"__symbolic":"method"}]}},"ɵe":{"__symbolic":"class","decorators":[{"__symbolic":"call","expression":{"__symbolic":"reference","module":"@angular/core","name":"Component","line":7,"character":1},"arguments":[{"selector":"lib-gmaillogin","template":"<button class=\"btn google-btn social-btn btn-google\" (click)=\"signInWithGoogle()\" type=\"button\">  <span> {{ btnText }}</span><i class=\"fa fa-google-plus\"></i></button>\n","styles":[""]}]}],"members":{"btnText":[{"__symbolic":"property","decorators":[{"__symbolic":"call","expression":{"__symbolic":"reference","module":"@angular/core","name":"Input","line":14,"character":3}}]}],"__ctor__":[{"__symbolic":"constructor","parameterDecorators":[null,[{"__symbolic":"call","expression":{"__symbolic":"reference","module":"@angular/core","name":"Inject","line":16,"character":5},"arguments":[{"__symbolic":"reference","name":"AuthConfigService"}]}],null,null],"parameters":[{"__symbolic":"reference","name":"ɵa"},{"__symbolic":"reference","name":"AuthConfig"},{"__symbolic":"reference","module":"@angular/router","name":"Router","line":16,"character":78},{"__symbolic":"reference","module":"@angular/router","name":"ActivatedRoute","line":16,"character":102}]}],"ngOnInit":[{"__symbolic":"method"}],"loadScript":[{"__symbolic":"method"}],"signInWithGoogle":[{"__symbolic":"method"}],"getGoogleProfile":[{"__symbolic":"method"}]}},"ɵf":{"__symbolic":"class","decorators":[{"__symbolic":"call","expression":{"__symbolic":"reference","module":"@angular/core","name":"Component","line":5,"character":1},"arguments":[{"selector":"td-log-out","template":"<a (click)=\"signOut()\" href=\"javascript:void(0)\"> Log Out</a>","styles":[""]}]}],"members":{"__ctor__":[{"__symbolic":"constructor","parameterDecorators":[null,null,[{"__symbolic":"call","expression":{"__symbolic":"reference","module":"@angular/core","name":"Inject","line":12,"character":95},"arguments":[{"__symbolic":"reference","name":"AuthConfigService"}]}]],"parameters":[{"__symbolic":"reference","name":"ɵa"},{"__symbolic":"reference","module":"@angular/router","name":"Router","line":12,"character":85},{"__symbolic":"reference","name":"AuthConfig"}]}],"ngOnInit":[{"__symbolic":"method"}],"signOut":[{"__symbolic":"method"}]}},"ɵg":{"__symbolic":"class","decorators":[{"__symbolic":"call","expression":{"__symbolic":"reference","module":"@angular/core","name":"Component","line":7,"character":1},"arguments":[{"selector":"td-insta-login","template":"<a id=\"instagram-button\" (click)=\"instaSignIn()\" class=\"btn btn-block btn-social btn-instagram\">\n  <i class=\"fa fa-instagram\"></i>  {{btnText}}\n</a>\n\n","styles":[""]}]}],"members":{"btnText":[{"__symbolic":"property","decorators":[{"__symbolic":"call","expression":{"__symbolic":"reference","module":"@angular/core","name":"Input","line":16,"character":3}}]}],"__ctor__":[{"__symbolic":"constructor","parameterDecorators":[null,null,[{"__symbolic":"call","expression":{"__symbolic":"reference","module":"@angular/core","name":"Inject","line":22,"character":5},"arguments":[{"__symbolic":"reference","name":"AuthConfigService"}]}]],"parameters":[{"__symbolic":"reference","module":"@angular/router","name":"Router","line":20,"character":31},{"__symbolic":"reference","name":"ɵa"},{"__symbolic":"reference","name":"AuthConfig"}]}],"ngOnInit":[{"__symbolic":"method"}],"instaSignIn":[{"__symbolic":"method"}],"authenticateInstagram":[{"__symbolic":"method"}],"login_callback":[{"__symbolic":"method"}]}},"ɵh":{"__symbolic":"class","decorators":[{"__symbolic":"call","expression":{"__symbolic":"reference","module":"@angular/core","name":"Injectable","line":6,"character":1}}],"members":{"__ctor__":[{"__symbolic":"constructor","parameters":[{"__symbolic":"reference","name":"ɵa"}]}],"intercept":[{"__symbolic":"method"}]}},"ɵi":{"__symbolic":"class","decorators":[{"__symbolic":"call","expression":{"__symbolic":"reference","module":"@angular/core","name":"Injectable","line":8,"character":1}}],"members":{"__ctor__":[{"__symbolic":"constructor","parameters":[{"__symbolic":"reference","name":"ɵa"},{"__symbolic":"reference","module":"@angular/router","name":"Router","line":10,"character":86}]}],"intercept":[{"__symbolic":"method"}]}}},"origins":{"AioAuthV01Service":"./lib/aio-auth-v01.service","AioAuthV01Component":"./lib/aio-auth-v01.component","AioAuthV01Module":"./lib/aio-auth-v01.module","AuthConfig":"./lib/auth-config","AuthConfigService":"./lib/auth-config","AuthGuard":"./lib/_guards/auth.guard","ɵa":"./lib/_services/authentication.service","ɵb":"./lib/login/login.component","ɵc":"./lib/register/register.component","ɵd":"./lib/fblogin/fblogin.component","ɵe":"./lib/gmaillogin/gmaillogin.component","ɵf":"./lib/log-out/log-out.component","ɵg":"./lib/insta-login/insta-login.component","ɵh":"./lib/_helpers/jwt.interceptor","ɵi":"./lib/_helpers/error.interceptor"},"importAs":"aio-auth-v01"}